{"errors":[],"warnings":[],"namedChunkGroups":{"app":{"chunks":[7,0,6,2],"assets":["webpack-runtime-afa11973eddfc4b1bae5.js","webpack-runtime-afa11973eddfc4b1bae5.js.map","commons-e99bf30bb9514d9573f8.js","commons-e99bf30bb9514d9573f8.js.map","netlify-identity-widget-7b977308d9406db03147.js","netlify-identity-widget-7b977308d9406db03147.js.map","app-50ab09a78a7e147db0c7.js","app-50ab09a78a7e147db0c7.js.map"],"children":{},"childAssets":{}},"component---src-pages-404-js":{"chunks":[1,0,3],"assets":["styles.d5ef0abb16ee382cea7f.css","styles-96ea1c23eb1c27c83239.js","styles-96ea1c23eb1c27c83239.js.map","commons-e99bf30bb9514d9573f8.js","commons-e99bf30bb9514d9573f8.js.map","component---src-pages-404-js-937d1b115ca56d3e6694.js","component---src-pages-404-js-937d1b115ca56d3e6694.js.map"],"children":{},"childAssets":{}},"component---src-pages-index-js":{"chunks":[1,0,4],"assets":["styles.d5ef0abb16ee382cea7f.css","styles-96ea1c23eb1c27c83239.js","styles-96ea1c23eb1c27c83239.js.map","commons-e99bf30bb9514d9573f8.js","commons-e99bf30bb9514d9573f8.js.map","component---src-pages-index-js-055149fa3779b8e93a06.js","component---src-pages-index-js-055149fa3779b8e93a06.js.map"],"children":{},"childAssets":{}},"component---src-pages-page-2-js":{"chunks":[1,0,5],"assets":["styles.d5ef0abb16ee382cea7f.css","styles-96ea1c23eb1c27c83239.js","styles-96ea1c23eb1c27c83239.js.map","commons-e99bf30bb9514d9573f8.js","commons-e99bf30bb9514d9573f8.js.map","component---src-pages-page-2-js-9091273db8b77923343d.js","component---src-pages-page-2-js-9091273db8b77923343d.js.map"],"children":{},"childAssets":{}}},"assetsByChunkName":{"app":["webpack-runtime-afa11973eddfc4b1bae5.js","commons-e99bf30bb9514d9573f8.js","netlify-identity-widget-7b977308d9406db03147.js","app-50ab09a78a7e147db0c7.js"],"component---src-pages-404-js":["styles.d5ef0abb16ee382cea7f.css","styles-96ea1c23eb1c27c83239.js","commons-e99bf30bb9514d9573f8.js","component---src-pages-404-js-937d1b115ca56d3e6694.js"],"component---src-pages-index-js":["styles.d5ef0abb16ee382cea7f.css","styles-96ea1c23eb1c27c83239.js","commons-e99bf30bb9514d9573f8.js","component---src-pages-index-js-055149fa3779b8e93a06.js"],"component---src-pages-page-2-js":["styles.d5ef0abb16ee382cea7f.css","styles-96ea1c23eb1c27c83239.js","commons-e99bf30bb9514d9573f8.js","component---src-pages-page-2-js-9091273db8b77923343d.js"]}}